Metadata-Version: 1.0
Name: ndbd-probability
Version: 0.1
Summary: Normal and Binomial distributions
Home-page: UNKNOWN
Author: Nemanja Manojlovic
Author-email: manojlovic.developer@gmail.com
License: UNKNOWN
Platform: UNKNOWN
